PIE/__init__.py
PIE/adaptive_threshold.py
PIE/analysis_configuration.py
PIE/colony_edge_detect.py
PIE/colony_filters.py
PIE/colony_prop_compilation.py
PIE/command_line_interface.py
PIE/density_fit.py
PIE/fluor_threshold.py
PIE/general_testing_functions.py
PIE/growth_measurement.py
PIE/image_coloring.py
PIE/image_properties.py
PIE/movies.py
PIE/ported_matlab.py
PIE/track_colonies.py
PIE/version.py
PIE/PIE_data/param_descriptions.csv
PIE-1.0.1.dist-info/LICENSE
PIE-1.0.1.dist-info/METADATA
PIE-1.0.1.dist-info/WHEEL
PIE-1.0.1.dist-info/entry_points.txt
PIE-1.0.1.dist-info/top_level.txt
PIE-1.0.1.dist-info/RECORD
