Metadata-Version: 2.1
Name: PIE
Version: 1.0.1
Summary: Colony recognition and growth measurement for microbial imaging
Home-page: https://github.com/Siegallab/PIE
Author: Yevgeniy Plavskin, Shuang Li, Hyun Jung, Federica M. O. Sartori, Cassandra Buzby, Heiko Müller, Naomi Ziv, Sasha F. Levy, Mark L. Siegal
Author-email: eugene.plavskin@nyu.edu, sl2803@nyu.edu, mark.siegal@nyu.edu
License: MIT
Keywords: image-analysis microscopy
Platform: UNKNOWN
Classifier: License :: OSI Approved :: MIT License
Classifier: Operating System :: OS Independent
Classifier: Programming Language :: Python :: 3
Classifier: Programming Language :: Python :: 3.8
Classifier: Programming Language :: Python
Provides-Extra: tests
License-File: LICENSE
